LICENSE.rst
README.rst
SUPPORT.rst
builder.py
pyproject.toml
COPYRIGHT.rst
poetry.lock
coriolis/Unicorn.so
coriolis/CRL.so
coriolis/Anabatic.so
coriolis/Tutorial.so
coriolis/Constant.so
coriolis/Hurricane.so
coriolis/Etesian.so
coriolis/Analog.so
coriolis/Cfg.so
coriolis/Hurricane3.so
coriolis/Viewer.so
coriolis/Flute.so
coriolis/Katana.so
coriolis/Bora.so
coriolis/__init__.py
coriolis/share/cmake/Modules/FindUNICORN.cmake
coriolis/share/cmake/Modules/FindKATANA.cmake
coriolis/share/cmake/Modules/FindFLUTE.cmake
coriolis/share/cmake/Modules/FindSOLSTICE.cmake
coriolis/share/cmake/Modules/FindOPENACCESS.cmake
coriolis/share/cmake/Modules/FindCORIOLIS.cmake
coriolis/share/cmake/Modules/FindHURRICANE.cmake
coriolis/share/cmake/Modules/UseLATEX.cmake
coriolis/share/cmake/Modules/FindANABATIC.cmake
coriolis/share/cmake/Modules/FindEQUINOX.cmake
coriolis/share/cmake/Modules/FindETESIAN.cmake
coriolis/share/flute/3.1/POWV9.dat
coriolis/share/flute/3.1/POST9.dat
coriolis/bora/initHook.py
coriolis/cumulus/plugins/runDemo.py
coriolis/karakaze/oceane.py
coriolis/karakaze/__init__.py
coriolis/karakaze/analogdesign.py
coriolis/oroshi/stack.py
coriolis/oroshi/capacitorunit.py
coriolis/oroshi/nonunitcapacitor.py
coriolis/oroshi/wip_csp.py
coriolis/oroshi/capacitorrouted.py
coriolis/oroshi/multicapacitor.py
coriolis/oroshi/capacitorroutedsingle.py
coriolis/oroshi/capacitormatrix.py
coriolis/oroshi/resistor.py
coriolis/oroshi/wip_dp.py
coriolis/oroshi/wip_transistor.py
coriolis/oroshi/paramsmatrix.py
coriolis/oroshi/resistorsnake.py
coriolis/oroshi/__init__.py
coriolis/oroshi/capacitorvrtracks.py
coriolis/oroshi/dtr.py
coriolis/helpers/io.py
coriolis/helpers/utils.py
coriolis/helpers/overlay.py
coriolis/helpers/analogtechno.py
coriolis/helpers/technology.py
coriolis/helpers/__init__.py
coriolis/unicorn/initHook.py
coriolis/include/lefdef/defiTimingDisable.hpp
coriolis/include/lefdef/defzlib.hpp
coriolis_eda-2.5.4.dist-info/LICENSE.rst
coriolis_eda-2.5.4.dist-info/entry_points.txt
coriolis_eda-2.5.4.dist-info/RECORD
coriolis_eda-2.5.4.dist-info/METADATA
coriolis_eda-2.5.4.dist-info/WHEEL
