Metadata-Version: 2.1
Name: coriolis-eda
Version: 2.5.4
Summary: Place and Route for semiconductors
Home-page: https://github.com/lip6/coriolis
Author: Jean-Paul Chaput
Author-email: Jean-Paul.Chaput@lip6.fr
Requires-Python: >=3.8,<4.0
Classifier: Programming Language :: Python :: 3
Classifier: Programming Language :: Python :: 3.8
Classifier: Programming Language :: Python :: 3.9
Classifier: Programming Language :: Python :: 3.10
Classifier: Programming Language :: Python :: 3.11
Requires-Dist: find-libpython (>=0.3.0,<0.4.0)
Project-URL: Repository, https://github.com/lip6/coriolis
